aerodynamicspy/__init__.py
aerodynamicspy/airfoils/Airfoil.py
aerodynamicspy/airfoils/__init__.py
aerodynamicspy/airfoils/common_airfoils.py
aerodynamicspy-0.0.3.dist-info/LICENSE
aerodynamicspy-0.0.3.dist-info/METADATA
aerodynamicspy-0.0.3.dist-info/WHEEL
aerodynamicspy-0.0.3.dist-info/top_level.txt
aerodynamicspy-0.0.3.dist-info/RECORD
